pysinric-0.1.1.dist-info/DESCRIPTION.rst
pysinric-0.1.1.dist-info/METADATA
pysinric-0.1.1.dist-info/RECORD
pysinric-0.1.1.dist-info/WHEEL
pysinric-0.1.1.dist-info/metadata.json
pysinric-0.1.1.dist-info/top_level.txt
sinric/__init__.py
sinric/_cbhandler.py
sinric/_mainqueue.py
sinric/_sinric.py
sinric/_sinricsocket.py
