Metadata-Version: 2.0
Name: pysinric
Version: 0.1.1
Summary: A python package for your sinric alexa skill
Home-page: https://github.com/kakopappa/sinric
Author: dazzHere
Author-email: dhanushdazz@gmail.com
License: UNKNOWN
Keywords: alexa,alexa-skill,sinric,sinric-alexa-skill,alexa-home-automation
Platform: UNKNOWN
Classifier: Programming Language :: Python :: 3
Classifier: Programming Language :: Python :: 2
Classifier: Operating System :: OS Independent
Requires-Dist: websocket-client
